{"actions": 3475, "added_lines": 121299.0, "added_lines_30": 203926, "added_lines_365": 7486431, "added_lines_7": 47976, "authors": 51, "authors_30": 4, "authors_365": 16, "authors_7": 4, "avg_commits_author": 40.2857, "avg_commits_month": 25.9737, "avg_files_author": 6.7551, "avg_files_month": 4.3553, "branches": 27, "commits": 1974, "commits_30": 20, "commits_365": 240, "commits_7": 9, "committers": 44, "diff_netadded_lines_30": 39374, "diff_netadded_lines_365": 1631137, "diff_netadded_lines_7": 17115, "diff_netauthors_30": 1, "diff_netauthors_365": -2, "diff_netauthors_7": 2, "diff_netcommits_30": 5, "diff_netcommits_365": 16, "diff_netcommits_7": 5, "diff_netfiles_30": 15, "diff_netfiles_365": 266, "diff_netfiles_7": 20, "diff_netremoved_lines_30": 16330, "diff_netremoved_lines_365": 2190413, "diff_netremoved_lines_7": 4886, "files": 331, "files_30": 36, "files_365": 278, "files_7": 24, "first_date": "2003-04-14", "last_date": "2014-07-15", "percentage_added_lines_30": 23, "percentage_added_lines_365": 27, "percentage_added_lines_7": 55, "percentage_authors_30": 33, "percentage_authors_365": 11, "percentage_authors_7": 100, "percentage_commits_30": 33, "percentage_commits_365": 7, "percentage_commits_7": 125, "percentage_files_30": 71, "percentage_files_365": 2216, "percentage_files_7": 500, "percentage_removed_lines_30": 12, "percentage_removed_lines_365": 51, "percentage_removed_lines_7": 14, "removed_lines": 95081.0, "removed_lines_30": 146183, "removed_lines_365": 6436815, "removed_lines_7": 39367, "repositories": 1}