{"actions": 16345, "added_lines": 463795.0, "added_lines_30": 404408, "added_lines_365": 7418730, "added_lines_7": 189633, "authors": 76, "authors_30": 3, "authors_365": 27, "authors_7": 2, "avg_commits_author": 71.9726, "avg_commits_month": 58.3778, "avg_files_author": 26.4384, "avg_files_month": 21.4444, "branches": 43, "commits": 5254, "commits_30": 18, "commits_365": 292, "commits_7": 7, "committers": 73, "diff_netadded_lines_30": 127985, "diff_netadded_lines_365": 2254544, "diff_netadded_lines_7": 153163, "diff_netauthors_30": -3, "diff_netauthors_365": 7, "diff_netauthors_7": -1, "diff_netcommits_30": -3, "diff_netcommits_365": 24, "diff_netcommits_7": 2, "diff_netfiles_30": -14, "diff_netfiles_365": 1593, "diff_netfiles_7": 0, "diff_netremoved_lines_30": 95122, "diff_netremoved_lines_365": 2761754, "diff_netremoved_lines_7": 85073, "files": 1930, "files_30": 18, "files_365": 1641, "files_7": 6, "first_date": "2003-04-14", "last_date": "2014-10-24", "percentage_added_lines_30": 46, "percentage_added_lines_365": 43, "percentage_added_lines_7": 419, "percentage_authors_30": 50, "percentage_authors_365": 35, "percentage_authors_7": 33, "percentage_commits_30": 14, "percentage_commits_365": 8, "percentage_commits_7": 40, "percentage_files_30": 43, "percentage_files_365": 3318, "percentage_files_7": 0, "percentage_removed_lines_30": 62, "percentage_removed_lines_365": 77, "percentage_removed_lines_7": 253, "removed_lines": 400466.0, "removed_lines_30": 246401, "removed_lines_365": 6310789, "removed_lines_7": 118679, "repositories": 1}