{"ReviewsWaitingForReviewer": 311, "ReviewsWaitingForSubmitter": 949, "abandoned": 1443, "abandoned_30": 26, "abandoned_365": 573, "abandoned_7": 4, "active_core_reviewers": 85, "active_core_reviewers_30": 33, "active_core_reviewers_365": 74, "active_core_reviewers_7": 16, "closed": 10302, "closed_30": 244, "closed_365": 4944, "closed_7": 37, "diff_netabandoned_30": 1, "diff_netabandoned_365": -67, "diff_netabandoned_7": -2, "diff_netactive_core_reviewers_30": -1, "diff_netactive_core_reviewers_365": 8, "diff_netactive_core_reviewers_7": -5, "diff_netclosed_30": -110, "diff_netclosed_365": 493, "diff_netclosed_7": -13, "diff_netmerged_30": -111, "diff_netmerged_365": 560, "diff_netmerged_7": -11, "diff_netparticipants_30": 15, "diff_netparticipants_365": -2, "diff_netparticipants_7": -12, "diff_netpending_30": 4, "diff_netpending_365": -125, "diff_netpending_7": 2, "diff_netsent_patchsets_30": -58, "diff_netsent_patchsets_365": 1376, "diff_netsent_patchsets_7": -26, "diff_netsubmitted_30": -106, "diff_netsubmitted_365": 368, "diff_netsubmitted_7": -11, "diff_netsubmitters_30": 3, "diff_netsubmitters_365": -27, "diff_netsubmitters_7": -3, "diff_netvoted_patchsets_30": -15, "diff_netvoted_patchsets_365": 402, "diff_netvoted_patchsets_7": -28, "first_date": "2012-02-27", "inprogress": 0, "last_date": "2015-06-21", "merged": 8859, "merged_30": 218, "merged_365": 4371, "merged_7": 33, "new": 553, "opened": 553, "participants": 454, "participants_30": 109, "participants_365": 310, "participants_7": 53, "patchset_submitters": 347, "pending": 548, "pending_30": 87, "pending_365": 387, "pending_7": 35, "percentage_abandoned_30": 4, "percentage_abandoned_365": 10, "percentage_abandoned_7": 33, "percentage_active_core_reviewers_30": 2, "percentage_active_core_reviewers_365": 12, "percentage_active_core_reviewers_7": 23, "percentage_closed_30": 31, "percentage_closed_365": 11, "percentage_closed_7": 26, "percentage_merged_30": 33, "percentage_merged_365": 14, "percentage_merged_7": 25, "percentage_participants_30": 15, "percentage_participants_365": 0, "percentage_participants_7": 18, "percentage_pending_30": 4, "percentage_pending_365": 24, "percentage_pending_7": 6, "percentage_sent_patchsets_30": 3, "percentage_sent_patchsets_365": 7, "percentage_sent_patchsets_7": 6, "percentage_submitted_30": 24, "percentage_submitted_365": 7, "percentage_submitted_7": 13, "percentage_submitters_30": 5, "percentage_submitters_365": 11, "percentage_submitters_7": 10, "percentage_voted_patchsets_30": 2, "percentage_voted_patchsets_365": 4, "percentage_voted_patchsets_7": 18, "review_time_days_avg": 13.54, "review_time_days_median": 0.68, "review_time_pending_ReviewsWaitingForReviewer_days_avg": 212.25, "review_time_pending_ReviewsWaitingForReviewer_days_median": 153.36, "review_time_pending_days_avg": 264.53, "review_time_pending_days_median": 253.7, "review_time_pending_upload_ReviewsWaitingForReviewer_days_avg": 154.74, "review_time_pending_upload_ReviewsWaitingForReviewer_days_median": 81.14, "review_time_pending_upload_days_avg": 141.0, "review_time_pending_upload_days_median": 141.0, "reviewers": 267, "sent_patchsets": 41572, "sent_patchsets_30": 1536, "sent_patchsets_365": 20516, "sent_patchsets_7": 359, "submitted": 10850, "submitted_30": 331, "submitted_365": 5331, "submitted_7": 72, "submitters": 349, "submitters_30": 63, "submitters_365": 213, "submitters_7": 25, "voted_patchsets": 19062, "voted_patchsets_30": 610, "voted_patchsets_365": 9203, "voted_patchsets_7": 125}