{"ReviewsWaitingForReviewer": 5, "ReviewsWaitingForSubmitter": 130, "abandoned": 240, "abandoned_30": 15, "abandoned_365": 185, "abandoned_7": 1, "closed": 2889, "closed_30": 126, "closed_365": 1884, "closed_7": 24, "diff_netabandoned_30": 1, "diff_netabandoned_365": 130, "diff_netabandoned_7": -6, "diff_netclosed_30": 26, "diff_netclosed_365": 879, "diff_netclosed_7": 2, "diff_netmerged_30": 25, "diff_netmerged_365": 749, "diff_netmerged_7": 8, "diff_netpending_30": 3, "diff_netpending_365": -81, "diff_netpending_7": 1, "diff_netsubmitted_30": 29, "diff_netsubmitted_365": 798, "diff_netsubmitted_7": 3, "diff_netsubmitters_30": -2, "diff_netsubmitters_365": 9, "diff_netsubmitters_7": 0, "first_date": "2011-09-08", "inprogress": 0, "last_date": "2014-10-02", "merged": 2649, "merged_30": 111, "merged_365": 1699, "merged_7": 23, "new": 24, "opened": 24, "pending": 25, "pending_30": -4, "pending_365": -28, "pending_7": 2, "percentage_abandoned_30": 7, "percentage_abandoned_365": 236, "percentage_abandoned_7": 85, "percentage_closed_30": 26, "percentage_closed_365": 87, "percentage_closed_7": 9, "percentage_merged_30": 29, "percentage_merged_365": 78, "percentage_merged_7": 53, "percentage_pending_30": 42, "percentage_pending_365": 152, "percentage_pending_7": 100, "percentage_submitted_30": 31, "percentage_submitted_365": 75, "percentage_submitted_7": 13, "percentage_submitters_30": 10, "percentage_submitters_365": 23, "percentage_submitters_7": 0, "repositories": 211, "review_time_days_avg": 2.973729908485855, "review_time_days_median": 0.20434999999999998, "review_time_pending_ReviewsWaitingForReviewer_days_avg": 43.471679999999999, "review_time_pending_ReviewsWaitingForReviewer_days_median": 5.5282999999999998, "review_time_pending_days_avg": 101.76551666666664, "review_time_pending_days_median": 63.282499999999999, "review_time_pending_upload_ReviewsWaitingForReviewer_days_avg": 4.7616999999999994, "review_time_pending_upload_ReviewsWaitingForReviewer_days_median": 5.1989000000000001, "review_time_pending_upload_days_avg": 59.642670833333334, "review_time_pending_upload_days_median": 31.0501, "reviewers": 76, "submitted": 2914, "submitted_30": 122, "submitted_365": 1856, "submitted_7": 26, "submitters": 60, "submitters_30": 17, "submitters_365": 47, "submitters_7": 10}