{"ReviewsWaitingForReviewer": 5, "ReviewsWaitingForSubmitter": 2, "abandoned": 10, "abandoned_30": 0, "abandoned_365": 4, "abandoned_7": 0, "closed": 211, "closed_30": 5, "closed_365": 120, "closed_7": 0, "diff_netabandoned_30": 0, "diff_netabandoned_365": -2, "diff_netabandoned_7": 0, "diff_netclosed_30": -4, "diff_netclosed_365": 29, "diff_netclosed_7": -1, "diff_netmerged_30": -4, "diff_netmerged_365": 31, "diff_netmerged_7": -1, "diff_netpending_30": 0, "diff_netpending_365": 7, "diff_netpending_7": -2, "diff_netsubmitted_30": -4, "diff_netsubmitted_365": 36, "diff_netsubmitted_7": -3, "diff_netsubmitters_30": -1, "diff_netsubmitters_365": 11, "diff_netsubmitters_7": -1, "first_date": "2011-09-08", "inprogress": 0, "last_date": "2014-08-24", "merged": 201, "merged_30": 5, "merged_365": 116, "merged_7": 0, "new": 7, "opened": 7, "pending": 7, "pending_30": 2, "pending_365": 7, "pending_7": 0, "percentage_abandoned_30": 0, "percentage_abandoned_365": 33, "percentage_abandoned_7": 0, "percentage_closed_30": 44, "percentage_closed_365": 31, "percentage_closed_7": 100, "percentage_merged_30": 44, "percentage_merged_365": 36, "percentage_merged_7": 100, "percentage_pending_30": 0, "percentage_pending_365": 0, "percentage_pending_7": 100, "percentage_submitted_30": 36, "percentage_submitted_365": 39, "percentage_submitted_7": 100, "percentage_submitters_30": 19, "percentage_submitters_365": 122, "percentage_submitters_7": 50, "repositories": 214, "review_time_days_avg": 2.8190899470899478, "review_time_days_median": 0.7135, "review_time_pending_ReviewsWaitingForReviewer_days_avg": 73.142799999999994, "review_time_pending_ReviewsWaitingForReviewer_days_median": 58.256399999999999, "review_time_pending_days_avg": 64.123957142857151, "review_time_pending_days_median": 58.256399999999999, "review_time_pending_update_ReviewsWaitingForReviewer_days_avg": 68.462639999999993, "review_time_pending_update_ReviewsWaitingForReviewer_days_median": 58.256300000000003, "review_time_pending_update_days_avg": 53.837442857142854, "review_time_pending_update_days_median": 53.347900000000003, "reviewers": 30, "submitted": 218, "submitted_30": 7, "submitted_365": 127, "submitted_7": 0, "submitters": 20, "submitters_30": 4, "submitters_365": 20, "submitters_7": 1}