{"ReviewsWaitingForReviewer": 6, "ReviewsWaitingForSubmitter": 19, "abandoned": 56, "abandoned_30": 5, "abandoned_365": 56, "abandoned_7": 3, "closed": 636, "closed_30": 42, "closed_365": 636, "closed_7": 9, "diff_netabandoned_30": 4, "diff_netabandoned_365": 56, "diff_netabandoned_7": 3, "diff_netclosed_30": -9, "diff_netclosed_365": 636, "diff_netclosed_7": 5, "diff_netmerged_30": -13, "diff_netmerged_365": 580, "diff_netmerged_7": 2, "diff_netpending_30": 3, "diff_netpending_365": 25, "diff_netpending_7": 2, "diff_netsubmitted_30": -6, "diff_netsubmitted_365": 661, "diff_netsubmitted_7": 7, "diff_netsubmitters_30": 0, "diff_netsubmitters_365": 37, "diff_netsubmitters_7": -2, "first_date": "2011-09-08", "inprogress": 0, "last_date": "2014-07-22", "merged": 580, "merged_30": 37, "merged_365": 580, "merged_7": 6, "new": 25, "opened": 25, "pending": 25, "pending_30": 4, "pending_365": 25, "pending_7": 2, "percentage_abandoned_30": 400, "percentage_abandoned_365": 0, "percentage_abandoned_7": 0, "percentage_closed_30": 17, "percentage_closed_365": 0, "percentage_closed_7": 125, "percentage_merged_30": 26, "percentage_merged_365": 0, "percentage_merged_7": 50, "percentage_pending_30": 300, "percentage_pending_365": 0, "percentage_pending_7": 0, "percentage_submitted_30": 11, "percentage_submitted_365": 0, "percentage_submitted_7": 175, "percentage_submitters_30": 0, "percentage_submitters_365": 0, "percentage_submitters_7": 40, "repositories": 214, "review_time_days_avg": 3.2534595959596007, "review_time_days_median": 0.8683, "review_time_pending_ReviewsWaitingForReviewer_days_avg": 73.576650000000001, "review_time_pending_ReviewsWaitingForReviewer_days_median": 56.055950000000003, "review_time_pending_days_avg": 116.74152400000003, "review_time_pending_days_median": 116.8454, "review_time_pending_update_ReviewsWaitingForReviewer_days_avg": 48.845483333333341, "review_time_pending_update_ReviewsWaitingForReviewer_days_median": 31.033799999999999, "review_time_pending_update_days_avg": 99.434128000000015, "review_time_pending_update_days_median": 108.7891, "reviewers": 50, "submitted": 661, "submitted_30": 46, "submitted_365": 661, "submitted_7": 11, "submitters": 37, "submitters_30": 6, "submitters_365": 37, "submitters_7": 3}