{"ReviewsWaitingForReviewer": 16, "ReviewsWaitingForSubmitter": 3, "abandoned": 41, "abandoned_30": 2, "abandoned_365": 41, "abandoned_7": 0, "closed": 637, "closed_30": 53, "closed_365": 636, "closed_7": 8, "diff_netabandoned_30": -1, "diff_netabandoned_365": 41, "diff_netabandoned_7": 0, "diff_netclosed_30": 12, "diff_netclosed_365": 634, "diff_netclosed_7": -11, "diff_netmerged_30": 13, "diff_netmerged_365": 593, "diff_netmerged_7": -11, "diff_netpending_30": 6, "diff_netpending_365": 19, "diff_netpending_7": 2, "diff_netsubmitted_30": 18, "diff_netsubmitted_365": 653, "diff_netsubmitted_7": -9, "diff_netsubmitters_30": -5, "diff_netsubmitters_365": 35, "diff_netsubmitters_7": 0, "first_date": "2011-09-08", "inprogress": 0, "last_date": "2014-07-20", "merged": 596, "merged_30": 51, "merged_365": 595, "merged_7": 8, "new": 19, "opened": 19, "pending": 19, "pending_30": 8, "pending_365": 19, "pending_7": 2, "percentage_abandoned_30": 33, "percentage_abandoned_365": 0, "percentage_abandoned_7": 0, "percentage_closed_30": 29, "percentage_closed_365": 31700, "percentage_closed_7": 57, "percentage_merged_30": 34, "percentage_merged_365": 29650, "percentage_merged_7": 57, "percentage_pending_30": 300, "percentage_pending_365": 0, "percentage_pending_7": 0, "percentage_submitted_30": 41, "percentage_submitted_365": 32650, "percentage_submitted_7": 47, "percentage_submitters_30": 27, "percentage_submitters_365": 1750, "percentage_submitters_7": 0, "repositories": 214, "review_time_days_avg": 6.5681267326732655, "review_time_days_median": 0.9031, "review_time_pending_ReviewsWaitingForReviewer_days_avg": 89.285725000000014, "review_time_pending_ReviewsWaitingForReviewer_days_median": 51.000100000000003, "review_time_pending_days_avg": 83.993173684210547, "review_time_pending_days_median": 39.633899999999997, "review_time_pending_update_ReviewsWaitingForReviewer_days_avg": 50.589256249999991, "review_time_pending_update_ReviewsWaitingForReviewer_days_median": 19.095750000000002, "review_time_pending_update_days_avg": 49.020521052631565, "review_time_pending_update_days_median": 19.0808, "reviewers": 48, "submitted": 656, "submitted_30": 61, "submitted_365": 655, "submitted_7": 10, "submitters": 37, "submitters_30": 13, "submitters_365": 37, "submitters_7": 4}