{"ReviewsWaitingForReviewer": 32, "ReviewsWaitingForSubmitter": 220, "abandoned": 319, "abandoned_30": 8, "abandoned_365": 189, "abandoned_7": 2, "closed": 3835, "closed_30": 293, "closed_365": 2419, "closed_7": 55, "diff_netabandoned_30": -3, "diff_netabandoned_365": 59, "diff_netabandoned_7": 0, "diff_netclosed_30": 89, "diff_netclosed_365": 1003, "diff_netclosed_7": -44, "diff_netmerged_30": 92, "diff_netmerged_365": 944, "diff_netmerged_7": -44, "diff_netpending_30": -16, "diff_netpending_365": -18, "diff_netpending_7": -12, "diff_netsubmitted_30": 73, "diff_netsubmitted_365": 985, "diff_netsubmitted_7": -56, "diff_netsubmitters_30": -3, "diff_netsubmitters_365": 11, "diff_netsubmitters_7": -4, "first_date": "2011-09-08", "inprogress": 0, "last_date": "2014-11-26", "merged": 3516, "merged_30": 285, "merged_365": 2230, "merged_7": 53, "new": 84, "opened": 84, "pending": 84, "pending_30": 4, "pending_365": 33, "pending_7": -3, "percentage_abandoned_30": 27, "percentage_abandoned_365": 45, "percentage_abandoned_7": 0, "percentage_closed_30": 43, "percentage_closed_365": 70, "percentage_closed_7": 44, "percentage_merged_30": 47, "percentage_merged_365": 73, "percentage_merged_7": 45, "percentage_pending_30": 80, "percentage_pending_365": 35, "percentage_pending_7": 133, "percentage_submitted_30": 32, "percentage_submitted_365": 67, "percentage_submitted_7": 51, "percentage_submitters_30": 18, "percentage_submitters_365": 26, "percentage_submitters_7": 36, "repositories": 212, "review_time_days_avg": 5.0764368149580825, "review_time_days_median": 0.7261, "review_time_pending_ReviewsWaitingForReviewer_days_avg": 19.18418437499999, "review_time_pending_ReviewsWaitingForReviewer_days_median": 8.7500999999999998, "review_time_pending_days_avg": 63.550142857142859, "review_time_pending_days_median": 15.3421, "review_time_pending_upload_ReviewsWaitingForReviewer_days_avg": 15.546890625, "review_time_pending_upload_ReviewsWaitingForReviewer_days_median": 5.8609, "review_time_pending_upload_days_avg": 40.51731097560976, "review_time_pending_upload_days_median": 7.0164, "reviewers": 89, "submitted": 3919, "submitted_30": 297, "submitted_365": 2452, "submitted_7": 52, "submitters": 68, "submitters_30": 13, "submitters_365": 52, "submitters_7": 7}