{"diff_netsenders_30": 2, "diff_netsenders_365": -26, "diff_netsenders_7": -2, "diff_netsent_30": 10, "diff_netsent_365": -70, "diff_netsent_7": -9, "first_date": "2009-01-19", "last_date": "2015-09-24", "percentage_senders_30": 200, "percentage_senders_365": 78, "percentage_senders_7": 66, "percentage_sent_30": 1000, "percentage_sent_365": 80, "percentage_sent_7": 90, "repositories": 1, "senders": 119, "senders_30": 3, "senders_365": 7, "senders_7": 1, "senders_init": 69, "senders_response": 100, "sent": 1371, "sent_30": 11, "sent_365": 17, "sent_7": 1, "sent_response": 1090, "threads": 281}