{"changed": 490, "changed_30": 26, "changed_365": 389, "changed_7": 8, "changers": 239, "changers_30": 18, "changers_365": 208, "changers_7": 8, "closed": 425, "closed_30": 15, "closed_365": 317, "closed_7": 7, "closers": 57, "closers_30": 5, "closers_365": 49, "closers_7": 3, "diff_netchanged_30": -34, "diff_netchanged_365": 226, "diff_netchanged_7": 3, "diff_netchangers_30": 0, "diff_netchangers_365": 118, "diff_netchangers_7": 3, "diff_netclosed_30": -27, "diff_netclosed_365": 195, "diff_netclosed_7": 3, "diff_netclosers_30": 0, "diff_netclosers_365": 34, "diff_netclosers_7": 0, "diff_netopened_30": 3, "diff_netopened_365": 154, "diff_netopened_7": 4, "diff_netopeners_30": 3, "diff_netopeners_365": 45, "diff_netopeners_7": 4, "first_date": "2012-02-23", "last_date": "2014-10-17", "opened": 511, "opened_30": 15, "opened_365": 332, "opened_7": 5, "openers": 144, "openers_30": 12, "openers_365": 109, "openers_7": 5, "percentage_changed_30": 56, "percentage_changed_365": 138, "percentage_changed_7": 60, "percentage_changers_30": 0, "percentage_changers_365": 131, "percentage_changers_7": 60, "percentage_closed_30": 64, "percentage_closed_365": 159, "percentage_closed_7": 75, "percentage_closers_30": 0, "percentage_closers_365": 226, "percentage_closers_7": 0, "percentage_opened_30": 25, "percentage_opened_365": 86, "percentage_opened_7": 400, "percentage_openers_30": 33, "percentage_openers_365": 70, "percentage_openers_7": 400, "trackers": 1}