{"diff_netsenders_30": 18, "diff_netsenders_365": 21, "diff_netsenders_7": -7, "diff_netsent_30": 37, "diff_netsent_365": 171, "diff_netsent_7": -14, "first_date": "2002-02-08", "last_date": "2014-12-16", "percentage_senders_30": 200, "percentage_senders_365": 29, "percentage_senders_7": 53, "percentage_sent_30": 370, "percentage_sent_365": 68, "percentage_sent_7": 60, "repositories": 1, "senders": 467, "senders_30": 27, "senders_365": 93, "senders_7": 6, "senders_init": 310, "senders_response": 355, "sent": 7302, "sent_30": 47, "sent_365": 422, "sent_7": 9, "sent_response": 5984, "threads": 4526}