{"changed": 1125, "changed_30": 109, "changed_365": 449, "changed_7": 37, "changers": 202, "changers_30": 22, "changers_365": 86, "changers_7": 8, "closed": 1018, "closed_30": 70, "closed_365": 343, "closed_7": 24, "closers": 55, "closers_30": 7, "closers_365": 23, "closers_7": 4, "diff_netchanged_30": 6, "diff_netchanged_365": 183, "diff_netchanged_7": 13, "diff_netchangers_30": -1, "diff_netchangers_365": 22, "diff_netchangers_7": -5, "diff_netclosed_30": 8, "diff_netclosed_365": 161, "diff_netclosed_7": 13, "diff_netclosers_30": -3, "diff_netclosers_365": 8, "diff_netclosers_7": -1, "diff_netopened_30": -19, "diff_netopened_365": 367, "diff_netopened_7": -4, "diff_netopeners_30": -1, "diff_netopeners_365": 24, "diff_netopeners_7": -2, "first_date": "2009-02-20", "last_date": "2014-08-04", "opened": 1211, "opened_30": 76, "opened_365": 468, "opened_7": 11, "openers": 159, "openers_30": 16, "openers_365": 60, "openers_7": 6, "percentage_changed_30": 5, "percentage_changed_365": 68, "percentage_changed_7": 54, "percentage_changers_30": 4, "percentage_changers_365": 34, "percentage_changers_7": 38, "percentage_closed_30": 12, "percentage_closed_365": 88, "percentage_closed_7": 118, "percentage_closers_30": 30, "percentage_closers_365": 53, "percentage_closers_7": 19, "percentage_opened_30": 19, "percentage_opened_365": 363, "percentage_opened_7": 26, "percentage_openers_30": 5, "percentage_openers_365": 66, "percentage_openers_7": 25, "trackers": 1}