{"diff_netsenders_30": 3, "diff_netsenders_365": 10, "diff_netsenders_7": 2, "diff_netsent_30": 58, "diff_netsent_365": 595, "diff_netsent_7": -1, "first_date": "2002-02-08", "last_date": "2014-07-02", "percentage_senders_30": 13, "percentage_senders_365": 17, "percentage_senders_7": 50, "percentage_sent_30": 75, "percentage_sent_365": 169, "percentage_sent_7": 11, "repositories": 1, "senders": 279, "senders_30": 25, "senders_365": 68, "senders_7": 6, "senders_init": 235, "senders_response": 176, "sent": 8845, "sent_30": 135, "sent_365": 946, "sent_7": 8, "sent_response": 2641, "threads": 2224}