{"abandoned": 20, "abandoned_30": 1, "abandoned_365": 12, "abandoned_7": 0, "closed": 418, "closed_30": 10, "closed_365": 242, "closed_7": 0, "diff_netabandoned_30": 1, "diff_netabandoned_365": 4, "diff_netabandoned_7": 0, "diff_netclosed_30": 2, "diff_netclosed_365": 66, "diff_netclosed_7": -4, "diff_netmerged_30": 1, "diff_netmerged_365": 62, "diff_netmerged_7": -4, "diff_netpending_30": -2, "diff_netpending_365": -14, "diff_netpending_7": 1, "diff_netsubmitted_30": 0, "diff_netsubmitted_365": 52, "diff_netsubmitted_7": -3, "diff_netsubmitters_30": 0, "diff_netsubmitters_365": 0, "diff_netsubmitters_7": -1, "first_date": "2011-09-08", "inprogress": 0, "last_date": "2014-10-10", "merged": 398, "merged_30": 9, "merged_365": 230, "merged_7": 0, "new": 4, "opened": 4, "pending": 4, "pending_30": 1, "pending_365": -5, "pending_7": 1, "percentage_abandoned_30": 0, "percentage_abandoned_365": 50, "percentage_abandoned_7": 0, "percentage_closed_30": 25, "percentage_closed_365": 37, "percentage_closed_7": 100, "percentage_merged_30": 12, "percentage_merged_365": 36, "percentage_merged_7": 100, "percentage_pending_30": 66, "percentage_pending_365": 155, "percentage_pending_7": 0, "percentage_submitted_30": 0, "percentage_submitted_365": 28, "percentage_submitted_7": 75, "percentage_submitters_30": 0, "percentage_submitters_365": 0, "percentage_submitters_7": 50, "repositories": 212, "review_time_days_avg": 2.5879106870229003, "review_time_days_median": 0.1836, "review_time_pending_ReviewsWaitingForReviewer_days_avg": 9.9155999999999995, "review_time_pending_ReviewsWaitingForReviewer_days_median": 9.9155999999999995, "review_time_pending_days_avg": 17.014125, "review_time_pending_days_median": 13.98, "review_time_pending_upload_ReviewsWaitingForReviewer_days_avg": 2.9697, "review_time_pending_upload_ReviewsWaitingForReviewer_days_median": 2.9697, "review_time_pending_upload_days_avg": 9.1675250000000013, "review_time_pending_upload_days_median": 2.1502499999999998, "reviewers": 36, "submitted": 422, "submitted_30": 11, "submitted_365": 237, "submitted_7": 1, "submitters": 3, "submitters_30": 2, "submitters_365": 3, "submitters_7": 1}