{"abandoned": 22, "abandoned_30": 2, "abandoned_365": 12, "abandoned_7": 0, "closed": 227, "closed_30": 9, "closed_365": 122, "closed_7": 2, "diff_netabandoned_30": 1, "diff_netabandoned_365": 2, "diff_netabandoned_7": 0, "diff_netclosed_30": 4, "diff_netclosed_365": 17, "diff_netclosed_7": -1, "diff_netmerged_30": 3, "diff_netmerged_365": 15, "diff_netmerged_7": -1, "diff_netpending_30": -1, "diff_netpending_365": -6, "diff_netpending_7": 4, "diff_netsubmitted_30": 3, "diff_netsubmitted_365": 11, "diff_netsubmitted_7": 3, "diff_netsubmitters_30": 0, "diff_netsubmitters_365": 0, "diff_netsubmitters_7": 0, "first_date": "2011-09-08", "inprogress": 0, "last_date": "2015-01-23", "merged": 205, "merged_30": 7, "merged_365": 110, "merged_7": 2, "new": 22, "opened": 22, "pending": 22, "pending_30": 0, "pending_365": 8, "pending_7": 2, "percentage_abandoned_30": 100, "percentage_abandoned_365": 20, "percentage_abandoned_7": 0, "percentage_closed_30": 80, "percentage_closed_365": 16, "percentage_closed_7": 33, "percentage_merged_30": 75, "percentage_merged_365": 15, "percentage_merged_7": 33, "percentage_pending_30": 100, "percentage_pending_365": 42, "percentage_pending_7": 200, "percentage_submitted_30": 50, "percentage_submitted_365": 9, "percentage_submitted_7": 300, "percentage_submitters_30": 0, "percentage_submitters_365": 0, "percentage_submitters_7": 0, "repositories": 213, "review_time_days_avg": 14.718182296650719, "review_time_days_median": 1.3303, "review_time_pending_ReviewsWaitingForReviewer_days_avg": 268.37139999999994, "review_time_pending_ReviewsWaitingForReviewer_days_median": 313.35989999999998, "review_time_pending_days_avg": 249.95446818181819, "review_time_pending_days_median": 248.82484999999997, "review_time_pending_upload_ReviewsWaitingForReviewer_days_avg": 130.81370666666669, "review_time_pending_upload_ReviewsWaitingForReviewer_days_median": 168.8792, "review_time_pending_upload_days_avg": 126.93910454545457, "review_time_pending_upload_days_median": 130.84215, "reviewers": 76, "submitted": 249, "submitted_30": 9, "submitted_365": 130, "submitted_7": 4, "submitters": 1, "submitters_30": 1, "submitters_365": 1, "submitters_7": 1}