{"actions": 2140, "added_lines": 77375.0, "added_lines_30": 98.0, "added_lines_365": 62690.0, "added_lines_7": 50.0, "authors": 10, "authors_30": 2, "authors_365": 8, "authors_7": 2, "avg_commits_author": 32.7, "avg_commits_month": 21.8, "avg_files_author": 102.9, "avg_files_month": 68.6, "branches": 8, "commits": 327, "commits_30": 15, "commits_365": 278, "commits_7": 3, "committers": 10, "diff_netadded_lines_30": -13.0, "diff_netadded_lines_365": 46752.0, "diff_netadded_lines_7": 20.0, "diff_netauthors_30": -1, "diff_netauthors_365": 2, "diff_netauthors_7": 0, "diff_netcommits_30": -4, "diff_netcommits_365": 113, "diff_netcommits_7": -1, "diff_netfiles_30": -14, "diff_netfiles_365": 823, "diff_netfiles_7": 1, "diff_netnewauthors_30": 0, "diff_netnewauthors_365": -4, "diff_netnewauthors_7": 0, "diff_netremoved_lines_30": -11.0, "diff_netremoved_lines_365": 32350.0, "diff_netremoved_lines_7": -5.0, "files": 1029, "files_30": 19, "files_365": 1029, "files_7": 8, "first_date": "2014-06-20", "last_date": "2015-09-20", "newauthors": 10, "newauthors_30": 0, "newauthors_365": 0, "newauthors_7": 0, "percentage_added_lines_30": 11, "percentage_added_lines_365": 293, "percentage_added_lines_7": 66, "percentage_authors_30": 33, "percentage_authors_365": 33, "percentage_authors_7": 0, "percentage_commits_30": 21, "percentage_commits_365": 68, "percentage_commits_7": 25, "percentage_files_30": 42, "percentage_files_365": 399, "percentage_files_7": 14, "percentage_newauthors_30": 0, "percentage_newauthors_365": 100, "percentage_newauthors_7": 0, "percentage_removed_lines_30": 14, "percentage_removed_lines_365": 467, "percentage_removed_lines_7": 16, "removed_lines": 46125.0, "removed_lines_30": 64.0, "removed_lines_365": 39265.0, "removed_lines_7": 25.0, "repositories": 1}