{"actions": 252, "added_lines": 5120.0, "added_lines_30": 4373.0, "added_lines_365": 5976.0, "added_lines_7": 40.0, "authors": 8, "authors_30": 6, "authors_365": 9, "authors_7": 1, "avg_commits_author": 11.0, "avg_commits_month": 3.35, "avg_files_author": 5.57, "avg_files_month": 1.7, "branches": 2, "commits": 77, "commits_30": 84, "commits_365": 105, "commits_7": 4, "committers": 8, "diff_netadded_lines_30": 3682.0, "diff_netadded_lines_365": 5922.0, "diff_netadded_lines_7": -182.0, "diff_netauthors_30": 3, "diff_netauthors_365": 7, "diff_netauthors_7": -3, "diff_netcommits_30": 75, "diff_netcommits_365": 103, "diff_netcommits_7": -6, "diff_netfiles_30": 43, "diff_netfiles_365": 59, "diff_netfiles_7": -19, "diff_netnewauthors_30": 0, "diff_netnewauthors_365": -4, "diff_netnewauthors_7": 0, "diff_netremoved_lines_30": 2283.0, "diff_netremoved_lines_365": 2966.0, "diff_netremoved_lines_7": -66.0, "files": 39, "files_30": 59, "files_365": 62, "files_7": 6, "first_date": "2013-09-11", "last_date": "2015-09-02", "newauthors": 8, "newauthors_30": 0, "newauthors_365": 0, "newauthors_7": 0, "percentage_added_lines_30": 532, "percentage_added_lines_365": 10966, "percentage_added_lines_7": 81, "percentage_authors_30": 100, "percentage_authors_365": 350, "percentage_authors_7": 75, "percentage_commits_30": 833, "percentage_commits_365": 5150, "percentage_commits_7": 60, "percentage_files_30": 268, "percentage_files_365": 1966, "percentage_files_7": 76, "percentage_newauthors_30": 0, "percentage_newauthors_365": 100, "percentage_newauthors_7": 0, "percentage_removed_lines_30": 1066, "percentage_removed_lines_365": 10985, "percentage_removed_lines_7": 86, "removed_lines": 2892.0, "removed_lines_30": 2497.0, "removed_lines_365": 2993.0, "removed_lines_7": 10.0, "repositories": 1}