{"abandoned": 70, "abandoned_30": 7, "abandoned_365": 56, "abandoned_7": 0, "closed": 747, "closed_30": 62, "closed_365": 603, "closed_7": 4, "diff_netabandoned_30": 0, "diff_netabandoned_365": 42, "diff_netabandoned_7": -2, "diff_netclosed_30": -19, "diff_netclosed_365": 459, "diff_netclosed_7": -8, "diff_netmerged_30": -19, "diff_netmerged_365": 417, "diff_netmerged_7": -6, "diff_netpending_30": -17, "diff_netpending_365": -51, "diff_netpending_7": 4, "diff_netsubmitted_30": -36, "diff_netsubmitted_365": 408, "diff_netsubmitted_7": -4, "diff_netsubmitters_30": 0, "diff_netsubmitters_365": 0, "diff_netsubmitters_7": 0, "first_date": "2011-09-08", "inprogress": 0, "last_date": "2014-10-12", "merged": 677, "merged_30": 55, "merged_365": 547, "merged_7": 4, "new": 7, "opened": 7, "pending": 7, "pending_30": -18, "pending_365": -22, "pending_7": -3, "percentage_abandoned_30": 0, "percentage_abandoned_365": 300, "percentage_abandoned_7": 100, "percentage_closed_30": 23, "percentage_closed_365": 318, "percentage_closed_7": 66, "percentage_merged_30": 25, "percentage_merged_365": 320, "percentage_merged_7": 60, "percentage_pending_30": -1700, "percentage_pending_365": 175, "percentage_pending_7": 57, "percentage_submitted_30": 44, "percentage_submitted_365": 235, "percentage_submitted_7": 80, "percentage_submitters_30": 0, "percentage_submitters_365": 0, "percentage_submitters_7": 0, "repositories": 212, "review_time_days_avg": 16.71433534072898, "review_time_days_median": 2.2686, "review_time_pending_ReviewsWaitingForReviewer_days_avg": 53.562199999999997, "review_time_pending_ReviewsWaitingForReviewer_days_median": 22.6755, "review_time_pending_days_avg": 113.3510857142857, "review_time_pending_days_median": 27.536899999999999, "review_time_pending_upload_ReviewsWaitingForReviewer_days_avg": 15.004899999999999, "review_time_pending_upload_ReviewsWaitingForReviewer_days_median": 14.217700000000001, "review_time_pending_upload_days_avg": 58.407771428571429, "review_time_pending_upload_days_median": 15.468, "reviewers": 91, "submitted": 754, "submitted_30": 44, "submitted_365": 581, "submitted_7": 1, "submitters": 1, "submitters_30": 1, "submitters_365": 1, "submitters_7": 1}