{"actions": 370, "added_lines": 67411.0, "added_lines_30": 105453, "added_lines_365": 6762389, "added_lines_7": 11922, "authors": 15, "authors_30": 1, "authors_365": 6, "authors_7": 0, "avg_commits_author": 11.4615, "avg_commits_month": 4.3824, "avg_files_author": 13.0769, "avg_files_month": 5.0, "branches": 49, "commits": 149, "commits_30": 2, "commits_365": 54, "commits_7": 0, "committers": 14, "diff_netadded_lines_30": -77231, "diff_netadded_lines_365": 1695123, "diff_netadded_lines_7": -7500, "diff_netauthors_30": 0, "diff_netauthors_365": 2, "diff_netauthors_7": 0, "diff_netcommits_30": -3, "diff_netcommits_365": 41, "diff_netcommits_7": 0, "diff_netfiles_30": -3, "diff_netfiles_365": 76, "diff_netfiles_7": 0, "diff_netremoved_lines_30": -78035, "diff_netremoved_lines_365": 2292555, "diff_netremoved_lines_7": -10307, "files": 170, "files_30": 2, "files_365": 86, "files_7": 0, "first_date": "2003-04-14", "last_date": "2015-01-02", "percentage_added_lines_30": 42, "percentage_added_lines_365": 33, "percentage_added_lines_7": 38, "percentage_authors_30": 0, "percentage_authors_365": 50, "percentage_authors_7": 0, "percentage_commits_30": 60, "percentage_commits_365": 315, "percentage_commits_7": 0, "percentage_files_30": 60, "percentage_files_365": 760, "percentage_files_7": 0, "percentage_removed_lines_30": 50, "percentage_removed_lines_365": 64, "percentage_removed_lines_7": 67, "removed_lines": 35986.0, "removed_lines_30": 76443, "removed_lines_365": 5825960, "removed_lines_7": 4979, "repositories": 1}