{"actions": 4032, "added_lines": 303462.0, "added_lines_30": 250.0, "added_lines_365": 14228.0, "added_lines_7": 49.0, "authors": 63, "authors_30": 9, "authors_365": 27, "authors_7": 3, "avg_commits_author": 20.06, "avg_commits_month": 19.44, "avg_files_author": 15.11, "avg_files_month": 14.64, "branches": 92, "commits": 1244, "commits_30": 33, "commits_365": 377, "commits_7": 6, "committers": 63, "diff_netadded_lines_30": -772.0, "diff_netadded_lines_365": -19832.0, "diff_netadded_lines_7": -58.0, "diff_netauthors_30": 2, "diff_netauthors_365": -7, "diff_netauthors_7": -4, "diff_netcommits_30": -15, "diff_netcommits_365": 76, "diff_netcommits_7": -5, "diff_netfiles_30": -32, "diff_netfiles_365": -31, "diff_netfiles_7": -19, "diff_netnewauthors_30": 0, "diff_netnewauthors_365": -6, "diff_netnewauthors_7": 0, "diff_netremoved_lines_30": -285.0, "diff_netremoved_lines_365": -20545.0, "diff_netremoved_lines_7": -52.0, "files": 937, "files_30": 60, "files_365": 474, "files_7": 8, "first_date": "2010-05-11", "last_date": "2015-10-06", "newauthors": 63, "newauthors_30": 0, "newauthors_365": 2, "newauthors_7": 0, "percentage_added_lines_30": 75, "percentage_added_lines_365": 58, "percentage_added_lines_7": 54, "percentage_authors_30": 28, "percentage_authors_365": 20, "percentage_authors_7": 57, "percentage_commits_30": 31, "percentage_commits_365": 25, "percentage_commits_7": 45, "percentage_files_30": 34, "percentage_files_365": 6, "percentage_files_7": 70, "percentage_newauthors_30": 0, "percentage_newauthors_365": 75, "percentage_newauthors_7": 0, "percentage_removed_lines_30": 66, "percentage_removed_lines_365": 73, "percentage_removed_lines_7": 82, "removed_lines": 245647.0, "removed_lines_30": 144.0, "removed_lines_365": 7316.0, "removed_lines_7": 11.0, "repositories": 1}