{"actions": 546780, "added_lines": 20854526.0, "added_lines_30": 284411, "added_lines_365": 7338451, "added_lines_7": 102962, "authors": 831, "authors_30": 125, "authors_365": 384, "authors_7": 78, "avg_commits_author": 222.0097, "avg_commits_month": 1338.5401, "avg_files_author": 123.2736, "avg_files_month": 743.2409, "branches": 239, "commits": 183380, "commits_30": 3011, "commits_365": 38230, "commits_7": 700, "committers": 722, "diff_netadded_lines_30": 120046, "diff_netadded_lines_365": 1858048, "diff_netadded_lines_7": 66732, "diff_netauthors_30": -8, "diff_netauthors_365": 29, "diff_netauthors_7": -9, "diff_netcommits_30": 48, "diff_netcommits_365": -1127, "diff_netcommits_7": -27, "diff_netfiles_30": -964, "diff_netfiles_365": 29420, "diff_netfiles_7": 387, "diff_netremoved_lines_30": 27382, "diff_netremoved_lines_365": 2772123, "diff_netremoved_lines_7": 27695, "files": 101824, "files_30": 4695, "files_365": 54003, "files_7": 1722, "first_date": "2003-04-14", "last_date": "2014-09-27", "percentage_added_lines_30": 73, "percentage_added_lines_365": 33, "percentage_added_lines_7": 184, "percentage_authors_30": 6, "percentage_authors_365": 8, "percentage_authors_7": 10, "percentage_commits_30": 1, "percentage_commits_365": 2, "percentage_commits_7": 3, "percentage_files_30": 17, "percentage_files_365": 119, "percentage_files_7": 28, "percentage_removed_lines_30": 21, "percentage_removed_lines_365": 76, "percentage_removed_lines_7": 94, "removed_lines": 14119581.0, "removed_lines_30": 153052, "removed_lines_365": 6374705, "removed_lines_7": 57024, "repositories": 235}