{"changed": 50227, "changed_30": 2550, "changed_365": 20270, "changed_7": 213, "changers": 6978, "changers_30": 227, "changers_365": 1790, "changers_7": 47, "closed": 33389, "closed_30": 719, "closed_365": 9439, "closed_7": 44, "closers": 1626, "closers_30": 105, "closers_365": 496, "closers_7": 22, "diff_netchanged_30": 310, "diff_netchanged_365": 4927, "diff_netchanged_7": -1066, "diff_netchangers_30": -51, "diff_netchangers_365": -251, "diff_netchangers_7": -95, "diff_netclosed_30": -165, "diff_netclosed_365": 3418, "diff_netclosed_7": -175, "diff_netclosers_30": -9, "diff_netclosers_365": 145, "diff_netclosers_7": -35, "diff_netopened_30": -83, "diff_netopened_365": 2149, "diff_netopened_7": -155, "diff_netopeners_30": -34, "diff_netopeners_365": -100, "diff_netopeners_7": -51, "first_date": "2004-08-10", "last_date": "2014-11-21", "opened": 47487, "opened_30": 771, "opened_365": 11619, "opened_7": 46, "openers": 7663, "openers_30": 171, "openers_365": 1331, "openers_7": 29, "percentage_changed_30": 13, "percentage_changed_365": 32, "percentage_changed_7": 83, "percentage_changers_30": 18, "percentage_changers_365": 12, "percentage_changers_7": 66, "percentage_closed_30": 18, "percentage_closed_365": 56, "percentage_closed_7": 79, "percentage_closers_30": 7, "percentage_closers_365": 41, "percentage_closers_7": 61, "percentage_opened_30": 9, "percentage_opened_365": 22, "percentage_opened_7": 77, "percentage_openers_30": 16, "percentage_openers_365": 6, "percentage_openers_7": 63, "trackers": 150}