{"actions": 3892, "added_lines": 99397.0, "added_lines_30": 1350.0, "added_lines_365": 64021.0, "added_lines_7": 131.0, "authors": 76, "authors_30": 17, "authors_365": 53, "authors_7": 2, "avg_commits_author": 16.27, "avg_commits_month": 36.48, "avg_files_author": 14.54, "avg_files_month": 32.61, "branches": 1, "commits": 1204, "commits_30": 66, "commits_365": 516, "commits_7": 2, "committers": 76, "diff_netadded_lines_30": 684.0, "diff_netadded_lines_365": 35329.0, "diff_netadded_lines_7": -157.0, "diff_netauthors_30": 2, "diff_netauthors_365": 8, "diff_netauthors_7": -6, "diff_netcommits_30": 39, "diff_netcommits_365": 7, "diff_netcommits_7": -5, "diff_netfiles_30": 66, "diff_netfiles_365": 291, "diff_netfiles_7": -11, "diff_netnewauthors_30": 0, "diff_netnewauthors_365": -9, "diff_netnewauthors_7": 0, "diff_netremoved_lines_30": 896.0, "diff_netremoved_lines_365": -7167.0, "diff_netremoved_lines_7": -195.0, "files": 1076, "files_30": 127, "files_365": 775, "files_7": 9, "first_date": "2012-10-16", "last_date": "2015-08-12", "newauthors": 76, "newauthors_30": 0, "newauthors_365": 7, "newauthors_7": 0, "percentage_added_lines_30": 102, "percentage_added_lines_365": 123, "percentage_added_lines_7": 54, "percentage_authors_30": 13, "percentage_authors_365": 17, "percentage_authors_7": 75, "percentage_commits_30": 144, "percentage_commits_365": 1, "percentage_commits_7": 71, "percentage_files_30": 108, "percentage_files_365": 60, "percentage_files_7": 55, "percentage_newauthors_30": 0, "percentage_newauthors_365": 56, "percentage_newauthors_7": 0, "percentage_removed_lines_30": 367, "percentage_removed_lines_365": 50, "percentage_removed_lines_7": 85, "removed_lines": 24148.0, "removed_lines_30": 1140.0, "removed_lines_365": 6955.0, "removed_lines_7": 33.0, "repositories": 1}