{"abandoned": 1917, "abandoned_30": 114, "abandoned_365": 1624, "abandoned_7": 20, "closed": 25572, "closed_30": 1700, "closed_365": 21593, "closed_7": 359, "diff_netabandoned_30": -100, "diff_netabandoned_365": 141, "diff_netabandoned_7": -23, "diff_netclosed_30": -41, "diff_netclosed_365": 1699, "diff_netclosed_7": -119, "diff_netmerged_30": 59, "diff_netmerged_365": 1558, "diff_netmerged_7": -96, "diff_netpending_30": 112, "diff_netpending_365": 391, "diff_netpending_7": 45, "diff_netsubmitted_30": 71, "diff_netsubmitted_365": 2090, "diff_netsubmitted_7": -74, "diff_netsubmitters_30": 4, "diff_netsubmitters_365": 9, "diff_netsubmitters_7": 0, "inprogress": 0, "merged": 23655, "merged_30": 1586, "merged_365": 19969, "merged_7": 339, "new": 477, "opened": 477, "pending": 477, "pending_30": 175, "pending_365": 451, "pending_7": 87, "percentage_abandoned_30": 46, "percentage_abandoned_365": 9, "percentage_abandoned_7": 53, "percentage_closed_30": 2, "percentage_closed_365": 8, "percentage_closed_7": 24, "percentage_merged_30": 3, "percentage_merged_365": 8, "percentage_merged_7": 22, "percentage_pending_30": 177, "percentage_pending_365": 651, "percentage_pending_7": 107, "percentage_submitted_30": 3, "percentage_submitted_365": 10, "percentage_submitted_7": 14, "percentage_submitters_30": 6, "percentage_submitters_365": 11, "percentage_submitters_7": 0, "repositories": 213, "review_time_days_avg": 4.600166913686997, "review_time_days_median": 0.2549, "review_time_pending_ReviewsWaitingForReviewer_days_avg": 105.04055681265262, "review_time_pending_ReviewsWaitingForReviewer_days_median": 49.372900000000001, "review_time_pending_days_avg": 112.0506436246993, "review_time_pending_days_median": 63.197899999999997, "review_time_pending_update_ReviewsWaitingForReviewer_days_avg": 74.85068564476876, "review_time_pending_update_ReviewsWaitingForReviewer_days_median": 16.3794, "review_time_pending_update_days_avg": 77.402397032878795, "review_time_pending_update_days_median": 29.207899999999999, "reviewers": 532, "submitted": 26049, "submitted_30": 1875, "submitted_365": 22044, "submitted_7": 446, "submitters": 90, "submitters_30": 64, "submitters_365": 89, "submitters_7": 51}