{"actions": 384398, "added_lines": 90429330.0, "added_lines_30": 166276, "added_lines_365": 7534016, "added_lines_7": 27036, "authors": 137, "authors_30": 66, "authors_365": 108, "authors_7": 49, "avg_commits_author": 863.0458, "avg_commits_month": 843.7239, "avg_files_author": 696.4275, "avg_files_month": 680.8358, "branches": 173, "commits": 113059, "commits_30": 2096, "commits_365": 23592, "commits_7": 457, "committers": 136, "diff_netadded_lines_30": -256597, "diff_netadded_lines_365": 1478676, "diff_netadded_lines_7": -46164, "diff_netauthors_30": -4, "diff_netauthors_365": 4, "diff_netauthors_7": -4, "diff_netcommits_30": -207, "diff_netcommits_365": 925, "diff_netcommits_7": -58, "diff_netfiles_30": -962, "diff_netfiles_365": 28408, "diff_netfiles_7": -628, "diff_netremoved_lines_30": -211444, "diff_netremoved_lines_365": 2033398, "diff_netremoved_lines_7": -13584, "files": 91232, "files_30": 4005, "files_365": 52354, "files_7": 928, "first_date": "2003-04-14", "last_date": "2014-06-18", "percentage_added_lines_30": 60, "percentage_added_lines_365": 24, "percentage_added_lines_7": 63, "percentage_authors_30": 5, "percentage_authors_365": 3, "percentage_authors_7": 7, "percentage_commits_30": 8, "percentage_commits_365": 4, "percentage_commits_7": 11, "percentage_files_30": 19, "percentage_files_365": 118, "percentage_files_7": 40, "percentage_removed_lines_30": 61, "percentage_removed_lines_365": 45, "percentage_removed_lines_7": 30, "removed_lines": 66278590.0, "removed_lines_30": 132038, "removed_lines_365": 6461568, "removed_lines_7": 30417, "repositories": 233}