{"actions": 960, "added_lines": 26610.0, "added_lines_30": 165.0, "added_lines_365": 2311.0, "added_lines_7": 10.0, "authors": 41, "authors_30": 3, "authors_365": 18, "authors_7": 2, "avg_commits_author": 13.5, "avg_commits_month": 10.38, "avg_files_author": 6.6, "avg_files_month": 5.08, "branches": 82, "commits": 540, "commits_30": 24, "commits_365": 234, "commits_7": 3, "committers": 41, "diff_netadded_lines_30": 72.0, "diff_netadded_lines_365": -19661.0, "diff_netadded_lines_7": -9.0, "diff_netauthors_30": 1, "diff_netauthors_365": -2, "diff_netauthors_7": 0, "diff_netcommits_30": 5, "diff_netcommits_365": 77, "diff_netcommits_7": -2, "diff_netfiles_30": 6, "diff_netfiles_365": 30, "diff_netfiles_7": -4, "diff_netnewauthors_30": 0, "diff_netnewauthors_365": -4, "diff_netnewauthors_7": 0, "diff_netremoved_lines_30": 38.0, "diff_netremoved_lines_365": -19967.0, "diff_netremoved_lines_7": 1.0, "files": 264, "files_30": 29, "files_365": 232, "files_7": 4, "first_date": "2011-04-27", "last_date": "2015-09-15", "newauthors": 41, "newauthors_30": 0, "newauthors_365": 2, "newauthors_7": 0, "percentage_added_lines_30": 77, "percentage_added_lines_365": 89, "percentage_added_lines_7": 47, "percentage_authors_30": 50, "percentage_authors_365": 9, "percentage_authors_7": 0, "percentage_commits_30": 26, "percentage_commits_365": 49, "percentage_commits_7": 40, "percentage_files_30": 26, "percentage_files_365": 14, "percentage_files_7": 50, "percentage_newauthors_30": 0, "percentage_newauthors_365": 66, "percentage_newauthors_7": 0, "percentage_removed_lines_30": 100, "percentage_removed_lines_365": 95, "percentage_removed_lines_7": 20, "removed_lines": 17495.0, "removed_lines_30": 76.0, "removed_lines_365": 905.0, "removed_lines_7": 6.0, "repositories": 1}